chuk_artifacts/__init__.py
chuk_artifacts/access_control.py
chuk_artifacts/admin.py
chuk_artifacts/base.py
chuk_artifacts/batch.py
chuk_artifacts/config.py
chuk_artifacts/core.py
chuk_artifacts/exceptions.py
chuk_artifacts/grid.py
chuk_artifacts/metadata.py
chuk_artifacts/models.py
chuk_artifacts/namespace.py
chuk_artifacts/presigned.py
chuk_artifacts/provider_factory.py
chuk_artifacts/py.typed
chuk_artifacts/store.py
chuk_artifacts/types.py
chuk_artifacts/providers/__init__.py
chuk_artifacts/providers/filesystem.py
chuk_artifacts/providers/ibm_cos.py
chuk_artifacts/providers/memory.py
chuk_artifacts/providers/s3.py
chuk_artifacts/providers/vfs_adapter.py
chuk_artifacts-0.10.1.dist-info/METADATA
chuk_artifacts-0.10.1.dist-info/WHEEL
chuk_artifacts-0.10.1.dist-info/top_level.txt
chuk_artifacts-0.10.1.dist-info/RECORD
