Metadata-Version: 2.4
Name: chuk-artifacts
Version: 0.10.1
Summary: Chuk Artifacts provides a production-ready, modular artifact storage system that works seamlessly across multiple storage backends (memory, filesystem, AWS S3, IBM Cloud Object Storage) with Redis or memory-based metadata caching and strict session-based security.
Requires-Python: >=3.11
Requires-Dist: pydantic>=2.10.6
Requires-Dist: pyyaml>=6.0.2
Requires-Dist: aioboto3>=14.3.0
Requires-Dist: redis>=6.2.0
Requires-Dist: chuk-sessions>=0.5.2
Requires-Dist: chuk-virtual-fs>=0.3.1
Requires-Dist: dotenv>=0.9.9
Requires-Dist: asyncio>=3.4.3
Provides-Extra: dev
Requires-Dist: pytest>=8.3.5; extra == "dev"
Requires-Dist: ruff>=0.4.6; extra == "dev"
